matadi/__about__.py
matadi/__init__.py
matadi/_apply.py
matadi/_lab_compressible.py
matadi/_lab_incompressible.py
matadi/_material.py
matadi/_templates.py
matadi/_variable.py
matadi/math.py
matadi/models/__init__.py
matadi/models/_helpers.py
matadi/models/_hyperelasticity_anisotropic.py
matadi/models/_hyperelasticity_isotropic.py
matadi/models/_misc.py
matadi/models/_pseudo_elasticity.py
matadi/models/_templates.py
matadi/models/_viscoelasticity.py
matadi/models/microsphere/__init__.py
matadi/models/microsphere/_chain.py
matadi/models/microsphere/affine/__init__.py
matadi/models/microsphere/affine/_models.py
matadi/models/microsphere/nonaffine/__init__.py
matadi/models/microsphere/nonaffine/_models.py
matadi/models/microsphere/quadrature/__init__.py
matadi/models/microsphere/quadrature/_bazant_oh.py
matadi-0.4.0.dist-info/licenses/LICENSE
matadi-0.4.0.dist-info/METADATA
matadi-0.4.0.dist-info/WHEEL
matadi-0.4.0.dist-info/top_level.txt
matadi-0.4.0.dist-info/RECORD
