Metadata-Version: 2.4
Name: matadi
Version: 0.4.0
Summary: Material Definition with Automatic Differentiation
Author-email: Andreas Dutzler <a.dutzler@gmail.com>
License-Expression: GPL-3.0-or-later
Project-URL: Homepage, https://github.com/adtzlr/matadi
Project-URL: Documentation, https://github.com/adtzlr/matadi
Project-URL: Repository, https://github.com/adtzlr/matadi
Project-URL: Issues, https://github.com/adtzlr/matadi/issues
Keywords: python,constitution,automatic-differentiation,scientific-computing,fem,finite-elements-analysis,algorithmic-differentiation,hyperelasticity,constitutive-model
Classifier: Development Status :: 5 - Production/Stable
Classifier: Programming Language :: Python
Classifier: Intended Audience :: Science/Research
Classifier: Operating System :: OS Independent
Classifier: Programming Language :: Python
Classifier: Programming Language :: Python :: 3
Classifier: Programming Language :: Python :: 3.9
Classifier: Programming Language :: Python :: 3.10
Classifier: Programming Language :: Python :: 3.11
Classifier: Programming Language :: Python :: 3.12
Classifier: Programming Language :: Python :: 3.13
Classifier: Topic :: Scientific/Engineering
Classifier: Topic :: Scientific/Engineering :: Mathematics
Classifier: Topic :: Utilities
Requires-Python: >=3.9
License-File: LICENSE
Requires-Dist: casadi
Requires-Dist: numpy
Provides-Extra: all
Requires-Dist: matplotlib; extra == "all"
Requires-Dist: scipy; extra == "all"
Dynamic: license-file
